README.md
setup.py
checkvalues/__init__.py
checkvalues/checker.py
checkvalues/inter.py
checkvalues/solution.py
checkvalues.egg-info/PKG-INFO
checkvalues.egg-info/SOURCES.txt
checkvalues.egg-info/dependency_links.txt
checkvalues.egg-info/requires.txt
checkvalues.egg-info/top_level.txt