Metadata-Version: 2.1
Name: checkvalues
Version: 1.0.0
Summary: checkvalues
Home-page: https://github.com/PGM-Lab/bcause
Author: Rafael Cabañas
Author-email: rcabanas@ual.es
License: Apache License 2.0
Classifier: Intended Audience :: Developers
Classifier: Intended Audience :: Education
Classifier: Intended Audience :: Science/Research
Classifier: License :: OSI Approved :: Apache Software License
Classifier: Operating System :: POSIX :: Linux
Classifier: Operating System :: MacOS :: MacOS X
Classifier: Operating System :: Microsoft :: Windows
Classifier: Programming Language :: Python :: 3.8
Requires-Python: >=3.8
Requires-Dist: pandas<2.1,>1.1
Requires-Dist: numpy<1.26,>1.22
